{
	"archive" : {},
	"artifacts" : 
	[
		{
			"path" : "tests/libqitestutils.a"
		}
	],
	"backtrace" : 1,
	"backtraceGraph" : 
	{
		"commands" : 
		[
			"add_library",
			"target_link_libraries",
			"add_definitions",
			"include_directories",
			"target_include_directories"
		],
		"files" : 
		[
			"tests/CMakeLists.txt",
			"CMakeLists.txt"
		],
		"nodes" : 
		[
			{
				"file" : 0
			},
			{
				"command" : 0,
				"file" : 0,
				"line" : 5,
				"parent" : 0
			},
			{
				"command" : 1,
				"file" : 0,
				"line" : 14,
				"parent" : 0
			},
			{
				"file" : 1
			},
			{
				"command" : 2,
				"file" : 1,
				"line" : 22,
				"parent" : 3
			},
			{
				"command" : 2,
				"file" : 1,
				"line" : 21,
				"parent" : 3
			},
			{
				"command" : 2,
				"file" : 0,
				"line" : 1,
				"parent" : 0
			},
			{
				"command" : 3,
				"file" : 1,
				"line" : 135,
				"parent" : 3
			},
			{
				"command" : 3,
				"file" : 1,
				"line" : 416,
				"parent" : 3
			},
			{
				"command" : 3,
				"file" : 0,
				"line" : 3,
				"parent" : 0
			},
			{
				"command" : 4,
				"file" : 0,
				"line" : 13,
				"parent" : 0
			}
		]
	},
	"compileGroups" : 
	[
		{
			"compileCommandFragments" : 
			[
				{
					"fragment" : " -Wall -Wextra -std=gnu++14 -pthread    -fno-strict-aliasing "
				},
				{
					"fragment" : "-std=gnu++14"
				}
			],
			"defines" : 
			[
				{
					"backtrace" : 2,
					"define" : "BOOST_ALL_NO_LIB"
				},
				{
					"backtrace" : 4,
					"define" : "BOOST_ASIO_DISABLE_STD_CHRONO"
				},
				{
					"backtrace" : 2,
					"define" : "BOOST_ATOMIC_DYN_LINK"
				},
				{
					"backtrace" : 2,
					"define" : "BOOST_CHRONO_DYN_LINK"
				},
				{
					"backtrace" : 2,
					"define" : "BOOST_FILESYSTEM_DYN_LINK"
				},
				{
					"backtrace" : 5,
					"define" : "BOOST_FILESYSTEM_VERSION=3"
				},
				{
					"backtrace" : 2,
					"define" : "BOOST_PROGRAM_OPTIONS_DYN_LINK"
				},
				{
					"backtrace" : 2,
					"define" : "BOOST_RANDOM_DYN_LINK"
				},
				{
					"backtrace" : 2,
					"define" : "BOOST_REGEX_DYN_LINK"
				},
				{
					"backtrace" : 2,
					"define" : "BOOST_SYSTEM_DYN_LINK"
				},
				{
					"backtrace" : 2,
					"define" : "BOOST_THREAD_DYN_LINK"
				},
				{
					"backtrace" : 6,
					"define" : "QI_IS_TEST"
				}
			],
			"includes" : 
			[
				{
					"backtrace" : 7,
					"path" : "/home/chris/ros_ws/src/build/naoqi_libqi"
				},
				{
					"backtrace" : 8,
					"path" : "/home/chris/ros_ws/src/naoqi_libqi"
				},
				{
					"backtrace" : 9,
					"path" : "/home/chris/ros_ws/src/naoqi_libqi/tests/."
				},
				{
					"backtrace" : 10,
					"path" : "/home/chris/ros_ws/src/naoqi_libqi/tests/GTEST_INCLUDE_DIRS"
				}
			],
			"language" : "CXX",
			"languageStandard" : 
			{
				"backtraces" : 
				[
					1
				],
				"standard" : "14"
			},
			"sourceIndexes" : 
			[
				1
			]
		}
	],
	"dependencies" : 
	[
		{
			"backtrace" : 2,
			"id" : "qi::@6890427a1f51a3e7e1df"
		}
	],
	"id" : "qitestutils::@a44f0ac069e85531cdee",
	"name" : "qitestutils",
	"nameOnDisk" : "libqitestutils.a",
	"paths" : 
	{
		"build" : "tests",
		"source" : "tests"
	},
	"sourceGroups" : 
	[
		{
			"name" : "Header Files",
			"sourceIndexes" : 
			[
				0,
				2
			]
		},
		{
			"name" : "Source Files",
			"sourceIndexes" : 
			[
				1
			]
		}
	],
	"sources" : 
	[
		{
			"backtrace" : 1,
			"path" : "tests/qi/testutils/testutils.hpp",
			"sourceGroupIndex" : 0
		},
		{
			"backtrace" : 1,
			"compileGroupIndex" : 0,
			"path" : "tests/qi/testutils/testutils.cpp",
			"sourceGroupIndex" : 1
		},
		{
			"backtrace" : 1,
			"path" : "tests/qi/testutils/mockutils.hpp",
			"sourceGroupIndex" : 0
		}
	],
	"type" : "STATIC_LIBRARY"
}
